{
  "conflict": "Middle-East War",
  "updated_at": "2026-05-30T21:10:15.562211+00:00",
  "message_count": 986,
  "channels": [
    "N12chat",
    "manniefabian",
    "asafroz",
    "yediotnews25",
    "SharghDaily",
    "amitsegal",
    "presstv",
    "mamlekate",
    "kianmeli1",
    "Faytuks_Network",
    "rodast_omiddana",
    "naya_foriraq",
    "tzevaadom_en",
    "VahidOnline",
    "idf_telegram",
    "lelotsenzura",
    "rasedal3ado138e",
    "shin_persian",
    "almogboker78",
    "New_security8200",
    "inon_yttach",
    "redlinkleb",
    "pkpoi"
  ],
  "red_alerts": 41,
  "red_alerts_timeline": [
    0,
    4,
    1,
    3,
    0,
    2,
    1,
    0,
    0,
    0,
    0,
    0,
    5,
    3,
    3,
    3,
    5,
    1,
    2,
    3,
    0,
    3,
    2,
    0
  ],
  "combined_activity_timeline": [
    6,
    30,
    10,
    18,
    9,
    7,
    11,
    27,
    21,
    27,
    30,
    26,
    49,
    40,
    48,
    45,
    76,
    60,
    59,
    83,
    77,
    90,
    72,
    64
  ],
  "messages_by_channel": {
    "@N12chat": 114,
    "@manniefabian": 9,
    "@asafroz": 17,
    "@yediotnews25": 25,
    "@SharghDaily": 171,
    "@amitsegal": 9,
    "@presstv": 94,
    "@mamlekate": 2,
    "@Faytuks_Network": 21,
    "@rodast_omiddana": 29,
    "@naya_foriraq": 59,
    "@tzevaadom_en": 41,
    "@VahidOnline": 11,
    "@idf_telegram": 21,
    "@lelotsenzura": 13,
    "@rasedal3ado138e": 130,
    "@shin_persian": 8,
    "@almogboker78": 16,
    "@New_security8200": 68,
    "@inon_yttach": 9,
    "@redlinkleb": 111,
    "@pkpoi": 8
  },
  "recent_post_urls": {
    "N12chat": "https://t.me/N12chat/210022",
    "manniefabian": "https://t.me/manniefabian/58323",
    "asafroz": "https://t.me/asafroz/49675",
    "yediotnews25": "https://t.me/yediotnews25/130127",
    "SharghDaily": "https://t.me/SharghDaily/162923",
    "amitsegal": "https://t.me/amitsegal/61519",
    "presstv": "https://t.me/presstv/192020",
    "mamlekate": "https://t.me/mamlekate/103604",
    "kianmeli1": "https://t.me/kianmeli1/87684",
    "Faytuks_Network": "https://t.me/Faytuks_Network/3192",
    "rodast_omiddana": "https://t.me/rodast_omiddana/72171",
    "naya_foriraq": "https://t.me/naya_foriraq/76477",
    "tzevaadom_en": "https://t.me/tzevaadom_en/67727",
    "VahidOnline": "https://t.me/VahidOnline/75807",
    "idf_telegram": "https://t.me/idf_telegram/24000",
    "lelotsenzura": "https://t.me/lelotsenzura/92354",
    "rasedal3ado138e": "https://t.me/rasedal3ado138e/363768",
    "shin_persian": "https://t.me/shin_persian/6321",
    "almogboker78": "https://t.me/almogboker78/17222",
    "New_security8200": "https://t.me/New_security8200/200377",
    "inon_yttach": "https://t.me/inon_yttach/8402",
    "redlinkleb": "https://t.me/redlinkleb/18920",
    "pkpoi": "https://t.me/pkpoi/142309"
  },
  "cited_post_urls": {
    "manniefabian": "https://t.me/manniefabian/58321",
    "asafroz": "https://t.me/asafroz/49664",
    "Faytuks_Network": "https://t.me/Faytuks_Network/3184",
    "idf_telegram": "https://t.me/idf_telegram/23996",
    "presstv": "https://t.me/presstv/192016",
    "SharghDaily": "https://t.me/SharghDaily/162907",
    "shin_persian": "https://t.me/shin_persian/6316",
    "pkpoi": "https://t.me/pkpoi/142302",
    "rasedal3ado138e": "https://t.me/rasedal3ado138e/363765",
    "naya_foriraq": "https://t.me/naya_foriraq/76465",
    "VahidOnline": "https://t.me/VahidOnline/75806"
  },
  "media": [
    {
      "post_url": "https://t.me/redlinkleb/18920",
      "post_id": 18920,
      "channel": "redlinkleb",
      "ts": "2026-05-30T21:07:18+00:00"
    },
    {
      "post_url": "https://t.me/redlinkleb/18918",
      "post_id": 18918,
      "channel": "redlinkleb",
      "ts": "2026-05-30T20:58:48+00:00"
    },
    {
      "post_url": "https://t.me/redlinkleb/18917",
      "post_id": 18917,
      "channel": "redlinkleb",
      "ts": "2026-05-30T20:58:36+00:00"
    },
    {
      "post_url": "https://t.me/redlinkleb/18916",
      "post_id": 18916,
      "channel": "redlinkleb",
      "ts": "2026-05-30T20:56:02+00:00"
    },
    {
      "post_url": "https://t.me/rasedal3ado138e/363744",
      "post_id": 363744,
      "channel": "rasedal3ado138e",
      "ts": "2026-05-30T20:50:43+00:00"
    },
    {
      "post_url": "https://t.me/redlinkleb/18907",
      "post_id": 18907,
      "channel": "redlinkleb",
      "ts": "2026-05-30T20:44:46+00:00"
    },
    {
      "post_url": "https://t.me/redlinkleb/18906",
      "post_id": 18906,
      "channel": "redlinkleb",
      "ts": "2026-05-30T20:42:40+00:00"
    },
    {
      "post_url": "https://t.me/redlinkleb/18905",
      "post_id": 18905,
      "channel": "redlinkleb",
      "ts": "2026-05-30T20:42:07+00:00"
    },
    {
      "post_url": "https://t.me/redlinkleb/18904",
      "post_id": 18904,
      "channel": "redlinkleb",
      "ts": "2026-05-30T20:41:34+00:00"
    },
    {
      "post_url": "https://t.me/naya_foriraq/76475",
      "post_id": 76475,
      "channel": "naya_foriraq",
      "ts": "2026-05-30T20:40:02+00:00"
    },
    {
      "post_url": "https://t.me/redlinkleb/18903",
      "post_id": 18903,
      "channel": "redlinkleb",
      "ts": "2026-05-30T20:37:11+00:00"
    },
    {
      "post_url": "https://t.me/shin_persian/6321",
      "post_id": 6321,
      "channel": "shin_persian",
      "ts": "2026-05-30T20:35:43+00:00"
    },
    {
      "post_url": "https://t.me/redlinkleb/18902",
      "post_id": 18902,
      "channel": "redlinkleb",
      "ts": "2026-05-30T20:34:28+00:00"
    },
    {
      "post_url": "https://t.me/redlinkleb/18899",
      "post_id": 18899,
      "channel": "redlinkleb",
      "ts": "2026-05-30T20:30:15+00:00"
    },
    {
      "post_url": "https://t.me/presstv/192017",
      "post_id": 192017,
      "channel": "presstv",
      "ts": "2026-05-30T20:20:05+00:00"
    },
    {
      "post_url": "https://t.me/redlinkleb/18889",
      "post_id": 18889,
      "channel": "redlinkleb",
      "ts": "2026-05-30T20:19:36+00:00"
    },
    {
      "post_url": "https://t.me/naya_foriraq/76474",
      "post_id": 76474,
      "channel": "naya_foriraq",
      "ts": "2026-05-30T20:19:34+00:00"
    },
    {
      "post_url": "https://t.me/redlinkleb/18887",
      "post_id": 18887,
      "channel": "redlinkleb",
      "ts": "2026-05-30T20:18:56+00:00"
    },
    {
      "post_url": "https://t.me/redlinkleb/18886",
      "post_id": 18886,
      "channel": "redlinkleb",
      "ts": "2026-05-30T20:17:57+00:00"
    },
    {
      "post_url": "https://t.me/presstv/192015",
      "post_id": 192015,
      "channel": "presstv",
      "ts": "2026-05-30T20:01:36+00:00"
    }
  ],
  "post_images": {
    "amitsegal/61517": "data/media/amitsegal_61517.jpg",
    "amitsegal/61516": "data/media/amitsegal_61517.jpg",
    "amitsegal/61518": "data/media/amitsegal_61518.jpg",
    "Faytuks_Network/3183": "data/media/Faytuks_Network_3183.jpg",
    "Faytuks_Network/3182": "data/media/Faytuks_Network_3183.jpg",
    "Faytuks_Network/3188": "data/media/Faytuks_Network_3188.jpg",
    "Faytuks_Network/3187": "data/media/Faytuks_Network_3188.jpg",
    "Faytuks_Network/3190": "data/media/Faytuks_Network_3190.jpg",
    "VahidOnline/75797": "data/media/VahidOnline_75797.jpg",
    "VahidOnline/75798": "data/media/VahidOnline_75797.jpg",
    "VahidOnline/75799": "data/media/VahidOnline_75799.jpg",
    "VahidOnline/75800": "data/media/VahidOnline_75800.jpg",
    "VahidOnline/75802": "data/media/VahidOnline_75802.jpg",
    "VahidOnline/75801": "data/media/VahidOnline_75802.jpg",
    "VahidOnline/75804": "data/media/VahidOnline_75804.jpg",
    "VahidOnline/75803": "data/media/VahidOnline_75804.jpg",
    "VahidOnline/75805": "data/media/VahidOnline_75805.jpg",
    "VahidOnline/75806": "data/media/VahidOnline_75806.jpg",
    "VahidOnline/75807": "data/media/VahidOnline_75807.jpg"
  },
  "summary": "Hezbollah launched rockets toward Karmiel and the Western Galilee, with some intercepted by the IDF. Iran fired a ballistic missile at Kuwait and the US Navy disabled a Gambia‑flagged vessel near the Strait of Hormuz. Israeli civil defense raised red alerts across the northern confrontation line and tightened public safety guidelines.",
  "key_points": [
    "Hezbollah fired rockets from Lebanon at Karmiel and the Western Galilee; several were intercepted with no injuries reported (Source: @manniefabian/58321).",
    "Iran launched a ballistic missile toward Kuwait, violating the cease‑fire, after previously firing five cruise missiles toward the Strait of Hormuz (Source: @asafroz/49664).",
    "The US Navy shot a warning missile into the engine room of a Gambia‑flagged merchant ship attempting to breach the maritime blockade (Source: @asafroz/49669).",
    "US forces disabled a Gambia‑flagged vessel attempting to sail toward an Iranian port in the Gulf of Oman on May 29 (Source: @Faytuks_Network/3184).",
    "Israel’s Home Front Command issued red alerts across the northern confrontation line and updated civil defense guidelines, restricting school activities and public gatherings (Source: @idf_telegram/23996).",
    "IRGC unveiled a new attack speedboat capable of launching two 700‑km cruise missiles and operating in 3‑meter waves (Source: @presstv/192016).",
    "Iran and the United States reportedly reached an informal understanding to allow Iran access to $12 billion of blocked assets within 60 days (Source: @SharghDaily/162907)."
  ],
  "sentiment": "escalating",
  "intensity": 7,
  "sections": {
    "executive_summary": "Hezbollah rockets struck northern Israel with IDF interceptions; Iran’s missile launch at Kuwait and US naval actions in the Strait of Hormuz heightened regional tensions. Israeli civil defense raised red alerts and tightened public safety measures across the north. An informal Iran‑US financial accord and IRGC’s new speedboat further complicate the strategic landscape.",
    "iran": {
      "points": [
        "Iran launched a ballistic missile toward Kuwait, breaching the cease‑fire, following earlier launches of five cruise missiles toward the Strait of Hormuz, all intercepted by US forces (Source: @asafroz/49664).",
        "An informal agreement reported by SharghDaily states the United States will enable Iran to access $12 billion of blocked assets within 60 days, with conditions on vessel classifications (Source: @SharghDaily/162907).",
        "IRGC showcased a new attack speedboat capable of firing two 700‑km cruise missiles and operating in sea states up to 3 meters, indicating enhanced maritime strike capability (Source: @presstv/192016).",
        "Iranian state media noted that Fars News and regime websites are currently difficult to access, suggesting possible information control measures (Source: @shin_persian/6316)."
      ]
    },
    "israel": {
      "points": [
        "Hezbollah fired rockets from Lebanon at Karmiel and the Western Galilee; the IDF intercepted several, with no injuries reported (Source: @manniefabian/58321).",
        "Israel’s Home Front Command issued red alerts across the northern confrontation line, updating civil defense guidelines to limit school activities, public gatherings, and close beaches (Source: @idf_telegram/23996).",
        "Multiple alerts were activated for hostile aircraft incursions over northern regions, including the headland of Rosh Hanikra and the Upper Galilee, with at least one unmanned aircraft intercepted (Source: @idf_telegram/23981).",
        "The Israeli cabinet discussed possible renewal of rocket attacks on Beirut and further ground maneuvering in the north, indicating potential escalation (Source: @pkpoi/142302)."
      ]
    },
    "gaza_west_bank": {
      "points": []
    },
    "lebanon": {
      "points": [
        "Hezbollah launched rockets toward Israeli northern cities, with some intercepted by the IDF (Source: @manniefabian/58321).",
        "A post claimed the Israeli army has lost control in southern Lebanon and warned that tanks will not remain there (Source: @rasedal3ado138e/363765).",
        "Lebanese media reported the hardest day for forces in South Lebanon since the cease‑fire (Source: @rasedal3ado138e/363759).",
        "A statement from a Lebanese source suggested possible future rocket attacks on Beirut’s southern suburbs (Source: @naya_foriraq/76465)."
      ]
    },
    "syria_iraq": {
      "points": [
        "No explicit operational reports concerning Syria or Iraq were present in the provided messages."
      ]
    },
    "gulf_states": {
      "points": [
        "US Navy engaged a Gambia‑flagged merchant vessel near the Strait of Hormuz, firing a warning missile into its engine room after multiple warnings (Source: @asafroz/49669).",
        "US forces disabled a Gambia‑flagged vessel attempting to sail toward an Iranian port in the Gulf of Oman on May 29 (Source: @Faytuks_Network/3184).",
        "British Maritime Trade Operations Authority labeled the maritime security threat level in the Strait of Hormuz as extremely critical due to the blockade (Source: @Faytuks_Network/3176).",
        "Iranian officials warned that any vessel carrying threatening cargo or operated by hostile entities would be classified as non‑commercial and barred from passage (Source: @VahidOnline/75806)."
      ]
    },
    "key_developments": [
      "Hezbollah launched rockets from Lebanon at Karmiel and the Western Galilee, with several intercepted and no injuries reported (Source: @manniefabian/58321).",
      "Iran fired a ballistic missile toward Kuwait, violating the cease‑fire, after previously launching five cruise missiles toward the Strait of Hormuz that were intercepted by US forces (Source: @asafroz/49664).",
      "The US Navy shot a warning missile into the engine room of a Gambia‑flagged merchant ship after more than 20 warning shots, enforcing the maritime blockade (Source: @asafroz/49669).",
      "US forces disabled a Gambia‑flagged vessel attempting to sail toward an Iranian port in the Gulf of Oman on May 29 (Source: @Faytuks_Network/3184).",
      "Israel’s Home Front Command raised red alerts across the northern confrontation line and updated civil defense guidelines, restricting schools and public gatherings (Source: @idf_telegram/23996).",
      "IRGC unveiled a new attack speedboat capable of firing two 700‑km cruise missiles and operating in sea states up to 3 meters (Source: @presstv/192016).",
      "An informal Iran‑US understanding promises Iran access to $12 billion of blocked assets within 60 days, subject to vessel classification rules (Source: @SharghDaily/162907)."
    ],
    "threat_assessment": "The region faces a multi‑front escalation: Hezbollah’s rocket fire into northern Israel demonstrates continued Lebanese front volatility, while Iran’s ballistic missile launch at Kuwait signals a breach of regional cease‑fire norms. US naval enforcement in the Strait of Hormuz and Gulf of Oman underscores heightened maritime security risks for commercial shipping. Israel’s expanded civil defense measures reflect anticipation of further aerial or artillery threats from Lebanon, increasing the likelihood of broader hostilities.",
    "regional_response": "Israel has tightened civil defense protocols, limiting civilian movement and schooling in northern communities, and is preparing for possible retaliatory strikes. The United States continues to enforce a naval blockade, employing warning fire and direct engagement to deter vessels perceived as violating sanctions. Iran, while confronting external pressure, is advancing its naval strike capabilities and pursuing financial relief through informal talks with the United States.",
    "intelligence_notes": "Monitoring of Hezbollah launch sites in southern Lebanon is critical as intercepted rockets suggest improved Israeli air‑defense effectiveness. Continued surveillance of Iranian missile deployments, especially ballistic and cruise variants, is required to assess escalation thresholds. Maritime traffic in the Strait of Hormuz should be tracked for compliance with blockade directives, and any deviation may trigger further US naval action."
  }
}