{
  "entries": [
    {
      "date": "2026-05-15",
      "total": 130,
      "missiles": 0,
      "drones": 130
    },
    {
      "date": "2026-05-16",
      "total": 294,
      "missiles": 0,
      "drones": 294
    },
    {
      "date": "2026-05-17",
      "total": 287,
      "missiles": 0,
      "drones": 287
    },
    {
      "date": "2026-05-18",
      "total": 546,
      "missiles": 22,
      "drones": 524
    },
    {
      "date": "2026-05-19",
      "total": 209,
      "missiles": 0,
      "drones": 209
    },
    {
      "date": "2026-05-20",
      "total": 6,
      "missiles": 0,
      "drones": 6
    },
    {
      "date": "2026-05-21",
      "total": 116,
      "missiles": 0,
      "drones": 116
    },
    {
      "date": "2026-05-22",
      "total": 124,
      "missiles": 0,
      "drones": 124
    },
    {
      "date": "2026-05-23",
      "total": 124,
      "missiles": 0,
      "drones": 124
    }
  ]
}